AUTHORS
LICENSE
MANIFEST.in
README
setup.py
contentmanager/__init__.py
contentmanager/admin.py
contentmanager/fields.py
contentmanager/forms.py
contentmanager/managers.py
contentmanager/middleware.py
contentmanager/models.py
contentmanager/plugins.py
contentmanager/registry.py
contentmanager/search_indexes.py
contentmanager/urls.py
contentmanager/utils.py
contentmanager/views.py
contentmanager/fixtures/contentmanager_test.xml
contentmanager/static/contentmanager/css/contentmanager.css
contentmanager/static/contentmanager/css/jquery-ui-1.7.2.custom.css
contentmanager/static/contentmanager/css/images/ui-bg_flat_0_aaaaaa_40x100.png
contentmanager/static/contentmanager/css/images/ui-bg_flat_75_ffffff_40x100.png
contentmanager/static/contentmanager/css/images/ui-bg_glass_55_fbf9ee_1x400.png
contentmanager/static/contentmanager/css/images/ui-bg_glass_65_ffffff_1x400.png
contentmanager/static/contentmanager/css/images/ui-bg_glass_75_dadada_1x400.png
contentmanager/static/contentmanager/css/images/ui-bg_glass_75_e6e6e6_1x400.png
contentmanager/static/contentmanager/css/images/ui-bg_glass_95_fef1ec_1x400.png
contentmanager/static/contentmanager/css/images/ui-bg_highlight-soft_75_cccccc_1x100.png
contentmanager/static/contentmanager/css/images/ui-icons_222222_256x240.png
contentmanager/static/contentmanager/css/images/ui-icons_2e83ff_256x240.png
contentmanager/static/contentmanager/css/images/ui-icons_454545_256x240.png
contentmanager/static/contentmanager/css/images/ui-icons_888888_256x240.png
contentmanager/static/contentmanager/css/images/ui-icons_cd0a0a_256x240.png
contentmanager/static/contentmanager/js/jquery-ui-1.7.2.custom.min.js
contentmanager/static/contentmanager/js/jquery.contentmanager.js
contentmanager/static/contentmanager/js/jquery.form.js
contentmanager/static/contentmanager/js/jquery_utilities_mw.js
contentmanager/templates/contentmanager/ajax.html
contentmanager/templates/contentmanager/base.html
contentmanager/templates/contentmanager/block.html
django_contentmanager.egg-info/PKG-INFO
django_contentmanager.egg-info/SOURCES.txt
django_contentmanager.egg-info/dependency_links.txt
django_contentmanager.egg-info/not-zip-safe
django_contentmanager.egg-info/requires.txt
django_contentmanager.egg-info/top_level.txt