Metadata-Version: 1.0
Name: django-contentmanager
Version: 2012.5.9
Summary: A simple, pluggable content-manager for django.
Home-page: http://bitbucket.org/pterk/django-contentmanager/
Author: Peter van Kampen
Author-email: pterk@datatailors.com
License: BSD
Platform: UNKNOWN
Classifier: Development Status :: 4 - Beta
Classifier: Environment :: Web Environment
Classifier: Intended Audience :: Developers
Classifier: License :: OSI Approved :: BSD License
Classifier: Operating System :: OS Independent
Classifier: Programming Language :: Python
Classifier: Framework :: Django
